[{"name": " Brick Bank", "pieces": "2380", "minifigs": "5", "image": "https://images.brickset.com/sets/small/10251-1.jpg?201510121127"},
{"name": " Volkswagen Beetle", "pieces": "1167", "minifigs": null, "image": "https://images.brickset.com/sets/small/10252-1.jpg?201606140214"},
{"name": " Big Ben", "pieces": "4163", "minifigs": null, "image": "https://images.brickset.com/sets/small/10253-1.jpg?201605190256"},
{"name": " Winter Holiday Train", "pieces": "734", "minifigs": "5", "image": "https://images.brickset.com/sets/small/10254-1.jpg?201608110306"},
{"name": " XL Creative Brick Box", "pieces": "1600", "minifigs": null, "image": "https://images.brickset.com/sets/small/10654-1.jpg?201609271134"},
{"name": " Creative Building Set", "pieces": "583", "minifigs": null, "image": "https://images.brickset.com/sets/small/10702-1.jpg?201511230710"},
{"name": " Creative Building Basket", "pieces": "1000", "minifigs": null, "image": "https://images.brickset.com/sets/small/10705-1.jpg?201605201119"},
{"name": " Police Helicopter Chase", "pieces": "63", "minifigs": "2", "image": "https://images.brickset.com/sets/small/10720-1.jpg?201601050913"},
{"name": " Iron Man vs. Loki", "pieces": "66", "minifigs": "2", "image": "https://images.brickset.com/sets/small/10721-1.jpg?201601050913"},
{"name": " Snake Showdown", "pieces": "92", "minifigs": "2", "image": "https://images.brickset.com/sets/small/10722-1.jpg?201601050913"},
{"name": " Ariel's Dolphin Carriage", "pieces": "70", "minifigs": "1", "image": "https://images.brickset.com/sets/small/10723-1.jpg?201601050913"},
{"name": " Batman & Superman vs. Lex Luthor", "pieces": "164", "minifigs": "3", "image": "https://images.brickset.com/sets/small/10724-1.jpg?201605201119"},
{"name": " Lost Temple", "pieces": "172", "minifigs": "3", "image": "https://images.brickset.com/sets/small/10725-1.jpg?201601050913"},
{"name": " Stephanie's Horse Carriage", "pieces": "58", "minifigs": "1", "image": "https://images.brickset.com/sets/small/10726-1.jpg?201605201119"},
{"name": " Emma's Ice Cream Truck", "pieces": "136", "minifigs": "2", "image": "https://images.brickset.com/sets/small/10727-1.jpg?201605201119"},
{"name": " Mia's Vet Clinic", "pieces": "173", "minifigs": "2", "image": "https://images.brickset.com/sets/small/10728-1.jpg?201605201119"},
{"name": " Cinderella's Carriage", "pieces": "116", "minifigs": "2", "image": "https://images.brickset.com/sets/small/10729-1.jpg?201601050913"},
{"name": " Baby Animals", "pieces": "13", "minifigs": null, "image": "https://images.brickset.com/sets/small/10801-1.jpg?201511230710"},
{"name": " Savanna", "pieces": "18", "minifigs": "1", "image": "https://images.brickset.com/sets/small/10802-1.jpg?201511230710"},
{"name": " Arctic", "pieces": "40", "minifigs": "2", "image": "https://images.brickset.com/sets/small/10803-1.jpg?201511230710"},
{"name": " Jungle", "pieces": "86", "minifigs": "2", "image": "https://images.brickset.com/sets/small/10804-1.jpg?201511230710"},
{"name": " Around the World", "pieces": "163", "minifigs": "5", "image": "https://images.brickset.com/sets/small/10805-1.jpg?201601050913"},
{"name": " Horses", "pieces": "20", "minifigs": "1", "image": "https://images.brickset.com/sets/small/10806-1.jpg?201511230710"},
{"name": " Horse Trailer", "pieces": "15", "minifigs": "2", "image": "https://images.brickset.com/sets/small/10807-1.jpg?201511230710"},
{"name": " Little Plane", "pieces": "13", "minifigs": "1", "image": "https://images.brickset.com/sets/small/10808-1.jpg?201511230710"},
{"name": " Police Patrol", "pieces": "15", "minifigs": "2", "image": "https://images.brickset.com/sets/small/10809-1.jpg?201511230710"},
{"name": " Push Train", "pieces": "45", "minifigs": "2", "image": "https://images.brickset.com/sets/small/10810-1.jpg?201605201119"},
{"name": " Backhoe Loader", "pieces": "19", "minifigs": "1", "image": "https://images.brickset.com/sets/small/10811-1.jpg?201605201119"},
{"name": " Truck & Tracked Excavator", "pieces": "28", "minifigs": "2", "image": "https://images.brickset.com/sets/small/10812-1.jpg?201605201119"},
{"name": " Big Construction Site", "pieces": "67", "minifigs": "3", "image": "https://images.brickset.com/sets/small/10813-1.jpg?201605201119"},
{"name": " Tow Truck", "pieces": "28", "minifigs": "2", "image": "https://images.brickset.com/sets/small/10814-1.jpg?201511230710"},
{"name": " My First Rocket", "pieces": "18", "minifigs": null, "image": "https://images.brickset.com/sets/small/10815-1.jpg?201511230710"},
{"name": " My First Cars and Trucks", "pieces": "36", "minifigs": null, "image": "https://images.brickset.com/sets/small/10816-1.jpg?201511230710"},
{"name": " Creative Chest", "pieces": "70", "minifigs": null, "image": "https://images.brickset.com/sets/small/10817-1.jpg?201511230710"},
{"name": " My First Truck", "pieces": "29", "minifigs": "2", "image": "https://images.brickset.com/sets/small/10818-1.jpg?201511230710"},
{"name": " My First Garden", "pieces": "25", "minifigs": "2", "image": "https://images.brickset.com/sets/small/10819-1.jpg?201511230710"},
{"name": " Creative Construction Basket", "pieces": "110", "minifigs": "2", "image": "https://images.brickset.com/sets/small/10820-1.jpg?201605201119"},
{"name": " Sofia the First Magical Carriage", "pieces": "30", "minifigs": "1", "image": "https://images.brickset.com/sets/small/10822-1.jpg?201605201119"},
{"name": " Miles' Space Adventures", "pieces": "23", "minifigs": "1", "image": "https://images.brickset.com/sets/small/10824-1.jpg?201511230710"},
{"name": " Miles' Exo-Flex Suit", "pieces": "37", "minifigs": "1", "image": "https://images.brickset.com/sets/small/10825-1.jpg?201605201119"},
{"name": " Miles' Stellosphere Hangar", "pieces": "44", "minifigs": "1", "image": "https://images.brickset.com/sets/small/10826-1.jpg?201511230710"},
{"name": " Mickey & Friends Beach House", "pieces": "48", "minifigs": "3", "image": "https://images.brickset.com/sets/small/10827-1.jpg?201605200842"},
{"name": " Doc McStuffins' Pet Vet Care", "pieces": "30", "minifigs": "1", "image": "https://images.brickset.com/sets/small/10828-1.jpg?201605201119"},
{"name": " Mickey's Workshop", "pieces": "18", "minifigs": "1", "image": "https://images.brickset.com/sets/small/10829-1.jpg?201511230710"},
{"name": " Minnie's Caf\u00e9", "pieces": "27", "minifigs": "1", "image": "https://images.brickset.com/sets/small/10830-1.jpg?201511230710"},
{"name": " My First Caterpillar", "pieces": "19", "minifigs": null, "image": "https://images.brickset.com/sets/small/10831-1.jpg?201511230710"},
{"name": " City: Build Your Own Adventure parts", "pieces": "92", "minifigs": "1", "image": "https://images.brickset.com/sets/small/11911-1.jpg?201708220151"},
{"name": " LEGO Star Wars: Build Your Own Adventure", "pieces": "73", "minifigs": "1", "image": "/assets/images/misc/blankbox.gif"},
{"name": " Venice", "pieces": "212", "minifigs": null, "image": "https://images.brickset.com/sets/small/21026-1.jpg?201511230710"},
{"name": " Berlin", "pieces": "289", "minifigs": null, "image": "https://images.brickset.com/sets/small/21027-1.jpg?201511230710"},
{"name": " New York City", "pieces": "598", "minifigs": null, "image": "https://images.brickset.com/sets/small/21028-1.jpg?201511230710"},
{"name": " Buckingham Palace", "pieces": "780", "minifigs": null, "image": "https://images.brickset.com/sets/small/21029-1.jpg?201608210825"},
{"name": " United States Capitol Building", "pieces": "1032", "minifigs": null, "image": "https://images.brickset.com/sets/small/21030-1.jpg?201608210825"},
{"name": " Burj Khalifa", "pieces": "333", "minifigs": null, "image": "https://images.brickset.com/sets/small/21031-1.jpg?201511230710"},
{"name": " The Iron Golem", "pieces": "208", "minifigs": "2", "image": "https://images.brickset.com/sets/small/21123-1.jpg?201602281011"},
{"name": " The End Portal", "pieces": "559", "minifigs": "3", "image": "https://images.brickset.com/sets/small/21124-1.jpg?201602281011"},
{"name": " The Jungle Tree House", "pieces": "706", "minifigs": "4", "image": "https://images.brickset.com/sets/small/21125-1.jpg?201602281011"},
{"name": " The Wither", "pieces": "318", "minifigs": "3", "image": "https://images.brickset.com/sets/small/21126-1.jpg?201602281011"},
{"name": " The Fortress", "pieces": "984", "minifigs": "4", "image": "https://images.brickset.com/sets/small/21127-1.jpg?201608210825"},
{"name": " The Village", "pieces": "1600", "minifigs": "8", "image": "https://images.brickset.com/sets/small/21128-1.jpg?201604140258"},
{"name": " Maze", "pieces": "769", "minifigs": null, "image": "https://images.brickset.com/sets/small/21305-1.jpg?201603050915"},
{"name": " The Beatles Yellow Submarine", "pieces": "553", "minifigs": "5", "image": "https://images.brickset.com/sets/small/21306-1.jpg?201610150938"},
{"name": " Caterham Seven 620R", "pieces": "771", "minifigs": null, "image": "https://images.brickset.com/sets/small/21307-1.jpg?201610041154"},
{"name": " First Order Star Destroyer", "pieces": "56", "minifigs": null, "image": "https://images.brickset.com/sets/small/30277-1.jpg?201601031117"},
{"name": " Poe's X-wing Fighter", "pieces": "64", "minifigs": null, "image": "https://images.brickset.com/sets/small/30278-1.jpg?201601150931"},
{"name": " Kylo Ren's Command Shuttle", "pieces": "43", "minifigs": null, "image": "https://images.brickset.com/sets/small/30279-1.jpg?201601181009"},
{"name": " Duck", "pieces": "4", "minifigs": null, "image": "https://images.brickset.com/sets/small/30321-1.jpg?201602281011"},
{"name": " Wildlife {Random bag}", "pieces": "7", "minifigs": null, "image": "https://images.brickset.com/sets/small/30322-1.jpg?201604260242"},
{"name": " Wildlife - Polar Bear", "pieces": null, "minifigs": null, "image": "https://images.brickset.com/sets/small/30322-2.jpg?201604260247"},
{"name": " Wildlife - Penguin", "pieces": null, "minifigs": null, "image": "https://images.brickset.com/sets/small/30322-3.jpg?201604260247"},
{"name": " Wildlife - Tortoise", "pieces": null, "minifigs": null, "image": "https://images.brickset.com/sets/small/30322-4.jpg?201604260246"},
{"name": " Wildlife - Lion Cub", "pieces": null, "minifigs": null, "image": "https://images.brickset.com/sets/small/30322-5.jpg?201604260246"},
{"name": " Wildlife - Elephant", "pieces": null, "minifigs": null, "image": "https://images.brickset.com/sets/small/30322-6.jpg?201604260246"},
{"name": " Prison Island Helicopter", "pieces": "46", "minifigs": "1", "image": "https://images.brickset.com/sets/small/30346-1.jpg?201601050923"},
{"name": " Fire Car", "pieces": "53", "minifigs": "1", "image": "https://images.brickset.com/sets/small/30347-1.jpg?201603060839"},
{"name": " Mini Dumper", "pieces": "45", "minifigs": "1", "image": "https://images.brickset.com/sets/small/30348-1.jpg?201601050923"},
{"name": " Sports Car", "pieces": "47", "minifigs": "1", "image": "https://images.brickset.com/sets/small/30349-1.jpg?201601050923"},
{"name": " Volcano Jackhammer", "pieces": "53", "minifigs": "1", "image": "https://images.brickset.com/sets/small/30350-1.jpg?201607190200"},
{"name": " Knight's Cycle", "pieces": "42", "minifigs": "1", "image": "https://images.brickset.com/sets/small/30371-1.jpg?201512160947"},
{"name": " Robin's Mini Fortrex", "pieces": "45", "minifigs": "1", "image": "https://images.brickset.com/sets/small/30372-1.jpg?201602150901"},
{"name": " Knighton Hyper Cannon", "pieces": "47", "minifigs": "1", "image": "https://images.brickset.com/sets/small/30373-1.jpg?201601191158"},
{"name": " The Lava Slinger", "pieces": "40", "minifigs": "1", "image": "https://images.brickset.com/sets/small/30374-1.jpg?201511180805"},
{"name": " Sira's Adventurous Airglider", "pieces": "24", "minifigs": "1", "image": "https://images.brickset.com/sets/small/30375-1.jpg?201602230650"},
{"name": " Cupcake Stall", "pieces": "28", "minifigs": "1", "image": "https://images.brickset.com/sets/small/30396-1.jpg?201606281050"},
{"name": " Olaf's Summertime Fun", "pieces": "48", "minifigs": "1", "image": "https://images.brickset.com/sets/small/30397-1.jpg?201602010902"},
{"name": " Adventure Camp Bridge", "pieces": "37", "minifigs": "1", "image": "https://images.brickset.com/sets/small/30398-1.jpg?201601150931"},
{"name": " Bowling Alley", "pieces": "51", "minifigs": "1", "image": "https://images.brickset.com/sets/small/30399-1.jpg?201602270142"},
{"name": " Skybound Plane", "pieces": "30", "minifigs": "1", "image": "https://images.brickset.com/sets/small/30421-1.jpg?201511180809"},
{"name": " Kai's Mini Dragon", "pieces": "39", "minifigs": "1", "image": "https://images.brickset.com/sets/small/30422-1.jpg?201603050915"},
{"name": " Anchor-Jet", "pieces": "38", "minifigs": "1", "image": "https://images.brickset.com/sets/small/30423-1.jpg?201602270142"},
{"name": " WU-CRU Training Dojo", "pieces": "43", "minifigs": "2", "image": "https://images.brickset.com/sets/small/30424-1.jpg?201603210934"},
{"name": " The Batmobile", "pieces": "63", "minifigs": null, "image": "https://images.brickset.com/sets/small/30446-1.jpg?201604090113"},
{"name": " Captain America's Motorcycle ", "pieces": "25", "minifigs": "1", "image": "https://images.brickset.com/sets/small/30447-1.jpg?201606010942"},
{"name": " Spider-Man vs. The Venom Symbiote", "pieces": "49", "minifigs": "1", "image": "https://images.brickset.com/sets/small/30448-1.jpg?201601191056"},
{"name": " Helicopter", "pieces": "47", "minifigs": null, "image": "https://images.brickset.com/sets/small/30471-1.jpg?201511180809"},
{"name": " Parrot", "pieces": "43", "minifigs": null, "image": "https://images.brickset.com/sets/small/30472-1.jpg?201605110829"},
{"name": " Racer", "pieces": "30", "minifigs": "1", "image": "https://images.brickset.com/sets/small/30473-1.jpg?201606060357"},
{"name": " Reindeer", "pieces": "77", "minifigs": null, "image": "https://images.brickset.com/sets/small/30474-1.jpg?201511180809"},
{"name": " Scooby-Doo", "pieces": "2", "minifigs": null, "image": "https://images.brickset.com/sets/small/30601-1.jpg?201605110824"},
{"name": " First Order Stormtrooper", "pieces": "7", "minifigs": "1", "image": "https://images.brickset.com/sets/small/30602-1.jpg?201603230839"},
{"name": " Batman Classic TV Series - Mr. Freeze", "pieces": "16", "minifigs": "1", "image": "https://images.brickset.com/sets/small/30603-1.jpg?201602270142"},
{"name": " Cosmic Boy", "pieces": "7", "minifigs": "1", "image": "https://images.brickset.com/sets/small/30604-1.jpg?201511020947"},
{"name": " Finn (FN-2187)", "pieces": "5", "minifigs": "1", "image": "https://images.brickset.com/sets/small/30605-1.jpg?201512160948"},
{"name": " Nightwing", "pieces": "6", "minifigs": "1", "image": "https://images.brickset.com/sets/small/30606-1.jpg?201604290650"},
{"name": " Desert Racers", "pieces": "65", "minifigs": null, "image": "https://images.brickset.com/sets/small/31040-1.jpg?201511180803"},
{"name": " Construction Vehicles", "pieces": "64", "minifigs": null, "image": "https://images.brickset.com/sets/small/31041-1.jpg?201511180803"},
{"name": " Super Soarer", "pieces": "100", "minifigs": null, "image": "https://images.brickset.com/sets/small/31042-1.jpg?201511180803"},
{"name": " Chopper Transporter", "pieces": "124", "minifigs": null, "image": "https://images.brickset.com/sets/small/31043-1.jpg?201511180803"},
{"name": " Park Animals", "pieces": "202", "minifigs": null, "image": "https://images.brickset.com/sets/small/31044-1.jpg?201511180803"},
{"name": " Ocean Explorer", "pieces": "213", "minifigs": null, "image": "https://images.brickset.com/sets/small/31045-1.jpg?201511180803"},
{"name": " Fast Car", "pieces": "222", "minifigs": null, "image": "https://images.brickset.com/sets/small/31046-1.jpg?201511180803"},
{"name": " Propeller Plane", "pieces": "230", "minifigs": null, "image": "https://images.brickset.com/sets/small/31047-1.jpg?201511230710"},
{"name": " Lakeside Lodge", "pieces": "368", "minifigs": "1", "image": "https://images.brickset.com/sets/small/31048-1.jpg?201511230710"},
{"name": " Twin Spin Helicopter", "pieces": "326", "minifigs": null, "image": "https://images.brickset.com/sets/small/31049-1.jpg?201605201119"},
{"name": " Corner Deli", "pieces": "467", "minifigs": "2", "image": "https://images.brickset.com/sets/small/31050-1.jpg?201511230710"},
{"name": " Lighthouse Point", "pieces": "528", "minifigs": "2", "image": "https://images.brickset.com/sets/small/31051-1.jpg?201605201119"},
{"name": " Vacation Getaways", "pieces": "792", "minifigs": "2", "image": "https://images.brickset.com/sets/small/31052-1.jpg?201605201119"},
{"name": " Treehouse Adventures", "pieces": "387", "minifigs": "2", "image": "https://images.brickset.com/sets/small/31053-1.jpg?201605201119"},
{"name": " Space Shuttle (Uniqlo edition)", "pieces": null, "minifigs": null, "image": "https://images.brickset.com/sets/small/40127-2.jpg?201611120859"},
{"name": " Robot (Uniqlo edition)", "pieces": null, "minifigs": null, "image": "https://images.brickset.com/sets/small/40128-2.jpg?201611120859"},
{"name": " Koala (Uniqlo edition)", "pieces": null, "minifigs": null, "image": "https://images.brickset.com/sets/small/40130-2.jpg?201611120859"},
{"name": " Parrot (Uniqlo edition)", "pieces": null, "minifigs": null, "image": "https://images.brickset.com/sets/small/40131-2.jpg?201611120858"},
{"name": " What am I?", "pieces": "536", "minifigs": "16", "image": "https://images.brickset.com/sets/small/40161-1.jpg?201605210924"},
{"name": " Minifigure Wedding Favour Set", "pieces": "89", "minifigs": "2", "image": "https://images.brickset.com/sets/small/40165-1.jpg?201603010826"},
{"name": " LEGOLAND Train", "pieces": "210", "minifigs": "4", "image": "https://images.brickset.com/sets/small/40166-1.jpg?201601050942"},
{"name": " My First Set", "pieces": "10", "minifigs": null, "image": "https://images.brickset.com/sets/small/40167-1.jpg?201603090954"},
{"name": " Personalised Mosaic Portrait", "pieces": null, "minifigs": null, "image": "https://images.brickset.com/sets/small/40179-1.jpg?201611171133"},
{"name": " Valentine's Cupid Dog", "pieces": "150", "minifigs": null, "image": "https://images.brickset.com/sets/small/40201-1.jpg?201511230710"},
{"name": " Easter Chick", "pieces": "111", "minifigs": null, "image": "https://images.brickset.com/sets/small/40202-1.jpg?201602281011"},
{"name": " Vampire and Bat", "pieces": "150", "minifigs": null, "image": "https://images.brickset.com/sets/small/40203-1.jpg?201608210825"},
{"name": " Pilgrim's Feast", "pieces": "163", "minifigs": null, "image": "https://images.brickset.com/sets/small/40204-1.jpg?201609271134"},
{"name": " Little Elf Helpers", "pieces": "238", "minifigs": null, "image": "https://images.brickset.com/sets/small/40205-1.jpg?201610281026"},
{"name": " LEGO Santa", "pieces": "155", "minifigs": null, "image": "https://images.brickset.com/sets/small/40206-1.jpg?201610281026"},
{"name": " Year of the Monkey", "pieces": "165", "minifigs": null, "image": "https://images.brickset.com/sets/small/40207-1.jpg?201512020117"},
{"name": " Polar Bear", "pieces": "40", "minifigs": null, "image": "https://images.brickset.com/sets/small/40208-1.jpg?201603210934"},
{"name": " Snowmobile", "pieces": "26", "minifigs": null, "image": "https://images.brickset.com/sets/small/40209-1.jpg?201602120333"},
{"name": " Bunny", "pieces": "49", "minifigs": null, "image": "https://images.brickset.com/sets/small/40210-1.jpg?201704051018"},
{"name": " Bee", "pieces": "34", "minifigs": null, "image": "https://images.brickset.com/sets/small/40211-1.jpg?201602270142"},
{"name": " Hedgehog", "pieces": "39", "minifigs": null, "image": "https://images.brickset.com/sets/small/40212-1.jpg?201602270142"},
{"name": " Seaplane", "pieces": "24", "minifigs": null, "image": "https://images.brickset.com/sets/small/40213-1.jpg?201602270142"},
{"name": " Frog", "pieces": "60", "minifigs": null, "image": "https://images.brickset.com/sets/small/40214-1.jpg?201603210934"},
{"name": " Apple", "pieces": "58", "minifigs": null, "image": "https://images.brickset.com/sets/small/40215-1.jpg?201603210934"},
{"name": " School Bus", "pieces": "65", "minifigs": null, "image": "https://images.brickset.com/sets/small/40216-1.jpg?201603210934"},
{"name": " Werewolf", "pieces": "52", "minifigs": null, "image": "https://images.brickset.com/sets/small/40217-1.jpg?201603210934"},
{"name": " Fox", "pieces": "39", "minifigs": null, "image": "https://images.brickset.com/sets/small/40218-1.jpg?201603210934"},
{"name": " Christmas Present", "pieces": "55", "minifigs": null, "image": "https://images.brickset.com/sets/small/40219-1.jpg?201603210934"},
{"name": " London Bus", "pieces": "118", "minifigs": null, "image": "https://images.brickset.com/sets/small/40220-1.jpg?201608080843"},
{"name": " Fountain", "pieces": "105", "minifigs": "2", "image": "https://images.brickset.com/sets/small/40221-1.jpg?201605201119"},
{"name": " Christmas Build-Up", "pieces": "250", "minifigs": null, "image": "https://images.brickset.com/sets/small/40222-1.jpg?201610030329"},
{"name": " Snowglobe", "pieces": "215", "minifigs": "1", "image": "https://images.brickset.com/sets/small/40223-1.jpg?201611220742"},
{"name": " Rio 2016 Mascots", "pieces": "197", "minifigs": null, "image": "https://images.brickset.com/sets/small/40225-1.jpg?201605110815"},
{"name": " Birthday Buddy", "pieces": "133", "minifigs": null, "image": "https://images.brickset.com/sets/small/40226-1.jpg?201607030638"},
{"name": " MSC Meraviglia", "pieces": "180", "minifigs": null, "image": "https://images.brickset.com/sets/small/40227-1.jpg?201601050923"},
{"name": " Geoffrey & Friends", "pieces": "133", "minifigs": "2", "image": "https://images.brickset.com/sets/small/40228-1.jpg?201605250950"},
{"name": " Rapunzel's Best Day Ever", "pieces": "145", "minifigs": "1", "image": "https://images.brickset.com/sets/small/41065-1.jpg?201605200842"},
{"name": " Anna & Kristoff's Sleigh Adventure", "pieces": "174", "minifigs": "2", "image": "https://images.brickset.com/sets/small/41066-1.jpg?201510280941"},
{"name": " Belle's Enchanted Castle", "pieces": "374", "minifigs": "8", "image": "https://images.brickset.com/sets/small/41067-1.jpg?201605201119"},
{"name": " Arendelle Castle Celebration", "pieces": "477", "minifigs": "6", "image": "https://images.brickset.com/sets/small/41068-1.jpg?201510280941"},
{"name": " Treasure's Day at the Pool", "pieces": "70", "minifigs": null, "image": "https://images.brickset.com/sets/small/41069-1.jpg?201511230710"},
{"name": " Birthday Party", "pieces": "191", "minifigs": "1", "image": "https://images.brickset.com/sets/small/41110-1.jpg?201511230710"},
{"name": " Party Train", "pieces": "109", "minifigs": "1", "image": "https://images.brickset.com/sets/small/41111-1.jpg?201511230710"},
{"name": " Party Cakes", "pieces": "50", "minifigs": null, "image": "https://images.brickset.com/sets/small/41112-1.jpg?201511230710"},
{"name": " Party Gift Shop", "pieces": "52", "minifigs": null, "image": "https://images.brickset.com/sets/small/41113-1.jpg?201511230710"},
{"name": " Party Styling", "pieces": "54", "minifigs": null, "image": "https://images.brickset.com/sets/small/41114-1.jpg?201601050913"},
{"name": " Emma's Creative Workshop", "pieces": "108", "minifigs": "1", "image": "https://images.brickset.com/sets/small/41115-1.jpg?201511230710"},
{"name": " Olivia's Exploration Car", "pieces": "185", "minifigs": "1", "image": "https://images.brickset.com/sets/small/41116-1.jpg?201511230710"},
{"name": " Pop Star TV Studio", "pieces": "194", "minifigs": "1", "image": "https://images.brickset.com/sets/small/41117-1.jpg?201511230710"},
{"name": " Heartlake Supermarket", "pieces": "313", "minifigs": "2", "image": "https://images.brickset.com/sets/small/41118-1.jpg?201511230710"},
{"name": " Heartlake Cupcake Cafe", "pieces": "439", "minifigs": "2", "image": "https://images.brickset.com/sets/small/41119-1.jpg?201511230710"},
{"name": " Adventure Camp Archery", "pieces": "114", "minifigs": "1", "image": "https://images.brickset.com/sets/small/41120-1.jpg?201511230710"},
{"name": " Adventure Camp Rafting", "pieces": "320", "minifigs": "2", "image": "https://images.brickset.com/sets/small/41121-1.jpg?201511230710"},
{"name": " Adventure Camp Tree House", "pieces": "726", "minifigs": "3", "image": "https://images.brickset.com/sets/small/41122-1.jpg?201511230710"},
{"name": " Foal's Washing Station", "pieces": "77", "minifigs": "1", "image": "https://images.brickset.com/sets/small/41123-1.jpg?201605201119"},
{"name": " Heartlake Puppy Daycare", "pieces": "286", "minifigs": "2", "image": "https://images.brickset.com/sets/small/41124-1.jpg?201605201119"},
{"name": " Horse Vet Trailer", "pieces": "370", "minifigs": "2", "image": "https://images.brickset.com/sets/small/41125-1.jpg?201605201119"},
{"name": " Heartlake Riding Club", "pieces": "575", "minifigs": "2", "image": "https://images.brickset.com/sets/small/41126-1.jpg?201605201119"},
{"name": " Amusement Park Arcade", "pieces": "174", "minifigs": "1", "image": "https://images.brickset.com/sets/small/41127-1.jpg?201605201119"},
{"name": " Amusement Park Space Ride", "pieces": "195", "minifigs": "1", "image": "https://images.brickset.com/sets/small/41128-1.jpg?201605201119"},
{"name": " Amusement Park Hot Dog Van", "pieces": "243", "minifigs": "2", "image": "https://images.brickset.com/sets/small/41129-1.jpg?201605201119"},
{"name": " Amusement Park Roller Coaster", "pieces": "1124", "minifigs": "4", "image": "https://images.brickset.com/sets/small/41130-1.jpg?201605201119"},
{"name": " Friends Advent Calendar", "pieces": "218", "minifigs": "2", "image": "https://images.brickset.com/sets/small/41131-1.jpg?201608210825"},
{"name": " Heartlake Party Shop", "pieces": "176", "minifigs": "2", "image": "https://images.brickset.com/sets/small/41132-1.jpg?201605210921"},
{"name": " Amusement Park Bumper Cars", "pieces": "424", "minifigs": "2", "image": "https://images.brickset.com/sets/small/41133-1.jpg?201605201119"},
{"name": " Heartlake Performance School", "pieces": "774", "minifigs": "3", "image": "https://images.brickset.com/sets/small/41134-1.jpg?201605210924"},
{"name": " Livi's Pop Star House", "pieces": "597", "minifigs": "2", "image": "https://images.brickset.com/sets/small/41135-1.jpg?201511230710"},
{"name": " Daisy's Beauty Salon", "pieces": "98", "minifigs": null, "image": "https://images.brickset.com/sets/small/41140-1.jpg?201511230710"},
{"name": " Pumpkin's Royal Carriage", "pieces": "79", "minifigs": null, "image": "https://images.brickset.com/sets/small/41141-1.jpg?201511230710"},
{"name": " Palace Pets Royal Castle", "pieces": "186", "minifigs": null, "image": "https://images.brickset.com/sets/small/41142-1.jpg?201511230710"},
{"name": " Emily Jones & the Baby Wind Dragon", "pieces": "80", "minifigs": "1", "image": "https://images.brickset.com/sets/small/41171-1.jpg?201602281011"},
{"name": " The Water Dragon Adventure", "pieces": "212", "minifigs": "1", "image": "https://images.brickset.com/sets/small/41172-1.jpg?201602281011"},
{"name": " Elvendale School of Dragons", "pieces": "230", "minifigs": "1", "image": "https://images.brickset.com/sets/small/41173-1.jpg?201602281011"},
{"name": " The Starlight Inn", "pieces": "343", "minifigs": "2", "image": "https://images.brickset.com/sets/small/41174-1.jpg?201602281011"},
{"name": " Fire Dragon's Lava Cave", "pieces": "441", "minifigs": "2", "image": "https://images.brickset.com/sets/small/41175-1.jpg?201602281011"},
{"name": " The Secret Market Place", "pieces": "691", "minifigs": "2", "image": "https://images.brickset.com/sets/small/41176-1.jpg?201602281011"},
{"name": " The Precious Crystal Mine", "pieces": "273", "minifigs": "2", "image": "https://images.brickset.com/sets/small/41177-1.jpg?201605201119"},
{"name": " The Dragon Sanctuary", "pieces": "585", "minifigs": "2", "image": "https://images.brickset.com/sets/small/41178-1.jpg?201605201119"},
{"name": " Queen Dragon's Rescue", "pieces": "833", "minifigs": "2", "image": "https://images.brickset.com/sets/small/41179-1.jpg?201605201119"},
{"name": " Ragana's Magic Shadow Castle", "pieces": "1014", "minifigs": "3", "image": "https://images.brickset.com/sets/small/41180-1.jpg?201605201119"},
{"name": " Superman & Wonder Woman", "pieces": null, "minifigs": null, "image": "https://images.brickset.com/sets/small/41490-1.jpg?201607210102"},
{"name": " Batman & The Joker", "pieces": null, "minifigs": null, "image": "https://images.brickset.com/sets/small/41491-1.jpg?201607210102"},
{"name": " Iron Man & Captain America", "pieces": null, "minifigs": null, "image": "https://images.brickset.com/sets/small/41492-1.jpg?201607210102"},
{"name": " Black Panther & Doctor Strange", "pieces": null, "minifigs": null, "image": "https://images.brickset.com/sets/small/41493-1.jpg?201607210103"},
{"name": " Kuffs", "pieces": "63", "minifigs": null, "image": "https://images.brickset.com/sets/small/41554-1.jpg?201602010902"},
{"name": " Busto", "pieces": "69", "minifigs": null, "image": "https://images.brickset.com/sets/small/41555-1.jpg?201602010902"},
{"name": " Tiketz", "pieces": "62", "minifigs": null, "image": "https://images.brickset.com/sets/small/41556-1.jpg?201602010902"},
{"name": " Camillot", "pieces": "64", "minifigs": null, "image": "https://images.brickset.com/sets/small/41557-1.jpg?201602010902"},
{"name": " Mixadel", "pieces": "63", "minifigs": null, "image": "https://images.brickset.com/sets/small/41558-1.jpg?201602010902"},
{"name": " Paladum", "pieces": "64", "minifigs": null, "image": "https://images.brickset.com/sets/small/41559-1.jpg?201602010902"},
{"name": " Jamzy", "pieces": "70", "minifigs": null, "image": "https://images.brickset.com/sets/small/41560-1.jpg?201602010902"},
{"name": " Tapsy", "pieces": "57", "minifigs": null, "image": "https://images.brickset.com/sets/small/41561-1.jpg?201602010902"},
{"name": " Trumpsy", "pieces": "54", "minifigs": null, "image": "https://images.brickset.com/sets/small/41562-1.jpg?201602010902"},
{"name": " Splasho", "pieces": "67", "minifigs": null, "image": "https://images.brickset.com/sets/small/41563-1.jpg?201605201119"},
{"name": " Aquad", "pieces": "70", "minifigs": null, "image": "https://images.brickset.com/sets/small/41564-1.jpg?201605201119"},
{"name": " Hydro", "pieces": "70", "minifigs": null, "image": "https://images.brickset.com/sets/small/41565-1.jpg?201605201119"},
{"name": " Sharx", "pieces": "55", "minifigs": null, "image": "https://images.brickset.com/sets/small/41566-1.jpg?201605201119"},
{"name": " Skulzy", "pieces": "66", "minifigs": null, "image": "https://images.brickset.com/sets/small/41567-1.jpg?201605201119"},
{"name": " Lewt", "pieces": "62", "minifigs": null, "image": "https://images.brickset.com/sets/small/41568-1.jpg?201605201119"},
{"name": " Surgeo", "pieces": "63", "minifigs": null, "image": "https://images.brickset.com/sets/small/41569-1.jpg?201605201119"},
{"name": " Skrubz", "pieces": "68", "minifigs": null, "image": "https://images.brickset.com/sets/small/41570-1.jpg?201605201119"},
{"name": " Tuth", "pieces": "67", "minifigs": null, "image": "https://images.brickset.com/sets/small/41571-1.jpg?201605201119"},
{"name": " Gobbol", "pieces": "62", "minifigs": null, "image": "https://images.brickset.com/sets/small/41572-1.jpg?201609271134"},
{"name": " Sweepz", "pieces": "61", "minifigs": null, "image": "https://images.brickset.com/sets/small/41573-1.jpg?201609271134"},
{"name": " Compax", "pieces": "66", "minifigs": null, "image": "https://images.brickset.com/sets/small/41574-1.jpg?201609271134"},
{"name": " Cobrax", "pieces": "64", "minifigs": null, "image": "https://images.brickset.com/sets/small/41575-1.jpg?201609271134"},
{"name": " Spinza", "pieces": "60", "minifigs": null, "image": "https://images.brickset.com/sets/small/41576-1.jpg?201609271134"},
{"name": " Mysto", "pieces": "64", "minifigs": null, "image": "https://images.brickset.com/sets/small/41577-1.jpg?201610041154"},
{"name": " Screeno", "pieces": "73", "minifigs": null, "image": "https://images.brickset.com/sets/small/41578-1.jpg?201609271134"},
{"name": " Camsta", "pieces": "62", "minifigs": null, "image": "https://images.brickset.com/sets/small/41579-1.jpg?201609271134"},
{"name": " Myke", "pieces": "63", "minifigs": null, "image": "https://images.brickset.com/sets/small/41580-1.jpg?201609271134"},
{"name": " Display Team Jet", "pieces": "113", "minifigs": null, "image": "https://images.brickset.com/sets/small/42044-1.jpg?201511180803"},
{"name": " Hydroplane Racer", "pieces": "180", "minifigs": null, "image": "https://images.brickset.com/sets/small/42045-1.jpg?201511180803"},
{"name": " Getaway Racer", "pieces": "170", "minifigs": null, "image": "https://images.brickset.com/sets/small/42046-1.jpg?201511180803"},
{"name": " Police Interceptor", "pieces": "185", "minifigs": null, "image": "https://images.brickset.com/sets/small/42047-1.jpg?201511180803"},
{"name": " Race Kart", "pieces": "345", "minifigs": null, "image": "https://images.brickset.com/sets/small/42048-1.jpg?201601050913"},
{"name": " Mine Loader", "pieces": "476", "minifigs": null, "image": "https://images.brickset.com/sets/small/42049-1.jpg?201601050913"},
{"name": " Drag Racer", "pieces": "647", "minifigs": null, "image": "https://images.brickset.com/sets/small/42050-1.jpg?201601050913"},
{"name": " Heavy Lift Helicopter", "pieces": "1042", "minifigs": null, "image": "https://images.brickset.com/sets/small/42052-1.jpg?201601050913"},
{"name": " Volvo EW160E", "pieces": "1166", "minifigs": null, "image": "https://images.brickset.com/sets/small/42053-1.jpg?201606181248"},
{"name": " CLAAS XERION 5000 TRAC VC", "pieces": "1977", "minifigs": null, "image": "https://images.brickset.com/sets/small/42054-1.jpg?201607190200"},
{"name": " Bucket Wheel Excavator", "pieces": "3929", "minifigs": null, "image": "https://images.brickset.com/sets/small/42055-1.jpg?201607190200"},
{"name": " Porsche 911 GT3 RS", "pieces": "2704", "minifigs": null, "image": "https://images.brickset.com/sets/small/42056-1.jpg?201604250159"},
{"name": " StoryTales Set", "pieces": "103", "minifigs": "6", "image": "https://images.brickset.com/sets/small/45014-1.jpg?201610170234"},
{"name": " Tubes Experiment Set", "pieces": "142", "minifigs": "4", "image": "https://images.brickset.com/sets/small/45016-1.jpg?201610140905"},
{"name": " Playground Set", "pieces": "98", "minifigs": "6", "image": "https://images.brickset.com/sets/small/45017-1.jpg?201610170235"},
{"name": " Build Me 'Emotions'", "pieces": "188", "minifigs": null, "image": "https://images.brickset.com/sets/small/45018-1.jpg?201605140851"},
{"name": " Creative LEGO DUPLO Brick Set", "pieces": null, "minifigs": null, "image": "https://images.brickset.com/sets/small/45019-1.jpg?201711301030"},
{"name": " Creative LEGO Brick Set", "pieces": "1000", "minifigs": null, "image": "/assets/images/misc/blankbox.gif"},
{"name": " WeDo 2.0 Core Set", "pieces": "280", "minifigs": null, "image": "https://images.brickset.com/sets/small/45300-1.jpg?202005210847"},
{"name": " WeDo 2.0 Smart Hub", "pieces": "1", "minifigs": null, "image": "https://images.brickset.com/sets/small/45301-1.jpg?201601110102"},
{"name": " WeDo 2.0 Smarthub Rechargeable Battery", "pieces": "1", "minifigs": null, "image": "https://images.brickset.com/sets/small/45302-1.jpg?201601110103"},
{"name": " WeDo 2.0 Medium Motor", "pieces": "1", "minifigs": null, "image": "https://images.brickset.com/sets/small/45303-1.jpg?201601110101"},
{"name": " WeDo 2.0 Motion Sensor", "pieces": "1", "minifigs": null, "image": "https://images.brickset.com/sets/small/45304-1.jpg?201601111259"},
{"name": " WeDo 2.0 Tilt Sensor", "pieces": "1", "minifigs": null, "image": "https://images.brickset.com/sets/small/45305-1.jpg?201601110104"},
{"name": " Animal Allies", "pieces": "2161", "minifigs": "2", "image": "https://images.brickset.com/sets/small/45802-1.jpg?201608191142"},
{"name": " Creature Craze Inspire Set", "pieces": "81", "minifigs": null, "image": "https://images.brickset.com/sets/small/45803-1.jpg?201610140906"},
{"name": " World Robot Olympiad Brick Set", "pieces": null, "minifigs": null, "image": "https://images.brickset.com/sets/small/45811-1.jpg?201809300650"},
{"name": " Airport Starter Set", "pieces": "81", "minifigs": "4", "image": "https://images.brickset.com/sets/small/60100-1.jpg?201605200842"},
{"name": " Airport Cargo Plane", "pieces": "157", "minifigs": "2", "image": "https://images.brickset.com/sets/small/60101-1.jpg?201605200842"},
{"name": " Airport VIP Service", "pieces": "364", "minifigs": "4", "image": "https://images.brickset.com/sets/small/60102-1.jpg?201605200842"},
{"name": " Airport Air Show", "pieces": "670", "minifigs": "6", "image": "https://images.brickset.com/sets/small/60103-1.jpg?201605200842"},
{"name": " Airport Passenger Terminal", "pieces": "694", "minifigs": "6", "image": "https://images.brickset.com/sets/small/60104-1.jpg?201605200842"},
{"name": " Fire ATV", "pieces": "64", "minifigs": "1", "image": "https://images.brickset.com/sets/small/60105-1.jpg?201511180804"},
{"name": " Fire Starter Set", "pieces": "90", "minifigs": "4", "image": "https://images.brickset.com/sets/small/60106-1.jpg?201511180804"},
{"name": " Fire Ladder Truck", "pieces": "214", "minifigs": "2", "image": "https://images.brickset.com/sets/small/60107-1.jpg?201511230710"},
{"name": " Fire Response Unit", "pieces": "257", "minifigs": "3", "image": "https://images.brickset.com/sets/small/60108-1.jpg?201511230710"},
{"name": " Fire Boat", "pieces": "412", "minifigs": "5", "image": "https://images.brickset.com/sets/small/60109-1.jpg?201511230710"},
{"name": " Fire Station", "pieces": "919", "minifigs": "6", "image": "https://images.brickset.com/sets/small/60110-1.jpg?201511230710"},
{"name": " Fire Utility Truck", "pieces": "368", "minifigs": "3", "image": "https://images.brickset.com/sets/small/60111-1.jpg?201511230710"},
{"name": " Fire Engine", "pieces": "376", "minifigs": "3", "image": "https://images.brickset.com/sets/small/60112-1.jpg?201511230710"},
{"name": " Rally Car", "pieces": "104", "minifigs": "1", "image": "https://images.brickset.com/sets/small/60113-1.jpg?201511180804"},
{"name": " Race Boat", "pieces": "95", "minifigs": "1", "image": "https://images.brickset.com/sets/small/60114-1.jpg?201511180804"},
{"name": " 4 x 4 Off Roader", "pieces": "176", "minifigs": "2", "image": "https://images.brickset.com/sets/small/60115-1.jpg?201511180804"},
{"name": " Ambulance Plane", "pieces": "183", "minifigs": "3", "image": "https://images.brickset.com/sets/small/60116-1.jpg?201511180804"},
{"name": " Van & Caravan", "pieces": "250", "minifigs": "2", "image": "https://images.brickset.com/sets/small/60117-1.jpg?201511230710"},
{"name": " Garbage Truck", "pieces": "248", "minifigs": "2", "image": "https://images.brickset.com/sets/small/60118-1.jpg?201511180804"},
{"name": " Ferry", "pieces": "301", "minifigs": "2", "image": "https://images.brickset.com/sets/small/60119-1.jpg?201601050913"},
{"name": " Volcano Starter Set", "pieces": "83", "minifigs": "4", "image": "https://images.brickset.com/sets/small/60120-1.jpg?201605200842"},
{"name": " Volcano Exploration Truck", "pieces": "175", "minifigs": "2", "image": "https://images.brickset.com/sets/small/60121-1.jpg?201605200842"},
{"name": " Volcano Crawler", "pieces": "324", "minifigs": "3", "image": "https://images.brickset.com/sets/small/60122-1.jpg?201605200842"},
{"name": " Volcano Supply Helicopter", "pieces": "330", "minifigs": "3", "image": "https://images.brickset.com/sets/small/60123-1.jpg?201605200842"},
{"name": " Volcano Exploration Base", "pieces": "824", "minifigs": "6", "image": "https://images.brickset.com/sets/small/60124-1.jpg?201605200842"},
{"name": " Volcano Heavy-Lift Helicopter", "pieces": "1277", "minifigs": "8", "image": "https://images.brickset.com/sets/small/60125-1.jpg?201605200842"},
{"name": " Tire Escape", "pieces": "47", "minifigs": "2", "image": "https://images.brickset.com/sets/small/60126-1.jpg?201511230710"},
{"name": " Prison Island Starter Set", "pieces": "92", "minifigs": "4", "image": "https://images.brickset.com/sets/small/60127-1.jpg?201511180804"},
{"name": " Police Pursuit", "pieces": "184", "minifigs": "2", "image": "https://images.brickset.com/sets/small/60128-1.jpg?201511180804"},
{"name": " Police Patrol Boat", "pieces": "200", "minifigs": "4", "image": "https://images.brickset.com/sets/small/60129-1.jpg?201511230710"},
{"name": " Prison Island", "pieces": "754", "minifigs": "8", "image": "https://images.brickset.com/sets/small/60130-1.jpg?201511230710"},
{"name": " Crooks Island", "pieces": "244", "minifigs": "3", "image": "https://images.brickset.com/sets/small/60131-1.jpg?201511230710"},
{"name": " Service Station", "pieces": "515", "minifigs": "4", "image": "https://images.brickset.com/sets/small/60132-1.jpg?201605200842"},
{"name": " City Advent Calendar", "pieces": "290", "minifigs": "7", "image": "https://images.brickset.com/sets/small/60133-1.jpg?201608210825"},
{"name": " People Pack - Fun in the Park", "pieces": "157", "minifigs": "15", "image": "https://images.brickset.com/sets/small/60134-1.jpg?201604090113"},
{"name": " 3-in-1 Super Pack", "pieces": null, "minifigs": null, "image": "https://images.brickset.com/sets/small/66537-1.jpg?201605300913"},
{"name": " Forests Value Pack", "pieces": null, "minifigs": null, "image": "/assets/images/misc/blankbox.gif"},
{"name": " Heartlake Value Pack", "pieces": null, "minifigs": null, "image": "https://images.brickset.com/sets/small/66539-1.jpg?201701230839"},
{"name": " City Volcano Value Pack", "pieces": null, "minifigs": null, "image": "https://images.brickset.com/sets/small/66540-1.jpg?201703071253"},
{"name": " City Fire Value Pack", "pieces": null, "minifigs": null, "image": "https://images.brickset.com/sets/small/66541-1.jpg?201701041050"},
{"name": " Microfighters Super Pack 3 in 1", "pieces": null, "minifigs": null, "image": "https://images.brickset.com/sets/small/66542-1.jpg?201610150935"},
{"name": " Microfighters Super Pack 3 in 1", "pieces": null, "minifigs": null, "image": "https://images.brickset.com/sets/small/66543-1.jpg?202002080420"},
{"name": " Mighty Micros Mighty Pack 3 in 1", "pieces": null, "minifigs": null, "image": "https://images.brickset.com/sets/small/66545-1.jpg?202005310857"},
{"name": " Axl's Tower Carrier, Extra Awesome Edition", "pieces": null, "minifigs": null, "image": "https://images.brickset.com/sets/small/66547-1.jpg?201611010109"}
]